<?xml version="1.0" encoding="UTF-8"?>
<objects serializationModel="Studio.02.01.00">
	<object class="AudioFile" id="{0c085ea8-8e26-4efe-ad06-62d469dfa978}">
		<property name="assetPath">
			<value>Player/Walking/Mud/Mud 2.wav</value>
		</property>
		<property name="frequencyInKHz">
			<value>44.0999985</value>
		</property>
		<property name="channelCount">
			<value>2</value>
		</property>
		<property name="length">
			<value>0.80612244897959184</value>
		</property>
		<relationship name="masterAssetFolder">
			<destination>{0107a68a-a665-42a7-a80a-dfc97087ab10}</destination>
		</relationship>
	</object>
</objects>
