<?xml version="1.0" encoding="UTF-8"?>
<objects serializationModel="Studio.02.01.00">
	<object class="AudioFile" id="{eba59434-51cd-4c1a-964e-2138cca4debd}">
		<property name="assetPath">
			<value>Player/Voice lines/Thoughts/Lost/What is happening 2.wav</value>
		</property>
		<property name="frequencyInKHz">
			<value>44.0999985</value>
		</property>
		<property name="channelCount">
			<value>2</value>
		</property>
		<property name="length">
			<value>0.95723356009070293</value>
		</property>
		<relationship name="masterAssetFolder">
			<destination>{0107a68a-a665-42a7-a80a-dfc97087ab10}</destination>
		</relationship>
	</object>
</objects>
